LICENSE
MANIFEST.in
README.md
requirements.txt
setup.py
unibasedb/__init__.py
unibasedb/__main__.py
unibasedb.egg-info/PKG-INFO
unibasedb.egg-info/SOURCES.txt
unibasedb.egg-info/dependency_links.txt
unibasedb.egg-info/entry_points.txt
unibasedb.egg-info/requires.txt
unibasedb.egg-info/top_level.txt
unibasedb/client/__init__.py
unibasedb/client/client.py
unibasedb/db/__init__.py
unibasedb/db/base.py
unibasedb/db/hnsw_unibase.py
unibasedb/db/inmemory_exact_unibase.py
unibasedb/db/service.py
unibasedb/db/executors/__init__.py
unibasedb/db/executors/hnsw_indexer.py
unibasedb/db/executors/inmemory_exact_indexer.py
unibasedb/db/executors/typed_executor.py
unibasedb/utils/__init__.py
unibasedb/utils/create_doc_type.py
unibasedb/utils/pass_parameters.py
unibasedb/utils/push_to_hubble.py
unibasedb/utils/sort_matches_by_score.py
unibasedb/utils/unify_input_output.py