Metadata-Version: 2.1
Name: unibasedb
Version: 0.0.1
Summary: The Python Unibase. Build your vector database from working as a library to scaling as a database in the cloud
Home-page: https://github.com/unibase-labs/unibasedb/
Download-URL: https://github.com/unibase-labs/unibasedb/tags
Author: Unibase Labs
Author-email: hello@unibase.cloud
License: Apache 2.0
Classifier: Development Status :: 5 - Production/Stable
Classifier: Intended Audience :: Developers
Classifier: License :: OSI Approved :: MIT License
Classifier: Programming Language :: Python
Classifier: Programming Language :: Python :: 3
Classifier: Programming Language :: Python :: 3.8
Classifier: Programming Language :: Python :: 3.9
Classifier: Programming Language :: Python :: 3.10
Classifier: Programming Language :: Python :: 3.11
Requires-Python: >=3.7
License-File: LICENSE
Requires-Dist: jina>=3.20.0
Requires-Dist: docarray[hnswlib]>=0.34.0
Provides-Extra: test
Requires-Dist: pytest; extra == "test"
Requires-Dist: pytest-asyncio; extra == "test"
Requires-Dist: pytest-repeat; extra == "test"
Requires-Dist: flaky; extra == "test"
Requires-Dist: pytest-timeout; extra == "test"
